{"content": "{\n  \"rules\": [\n    {\n      \"parameter\": \"gen.equipment_tag\",\n      \"operator\": \"exists\",\n      \"value\": null,\n      \"unit\": null,\n      \"condition\": null,\n      \"quote\": \"Maintain equipment-tag, purchase-order, serial-number, and source-lot traceability.\"\n    },\n    {\n      \"parameter\": \"gen.purchase_order\",\n      \"operator\": \"exists\",\n      \"value\": null,\n      \"unit\": null,\n      \"condition\": null,\n      \"quote\": \"Maintain equipment-tag, purchase-order, serial-number, and source-lot traceability.\"\n    },\n    {\n      \"parameter\": \"gen.serial_number\",\n      \"operator\": \"exists\",\n      \"value\": null,\n      \"unit\": null,\n      \"condition\": null,\n      \"quote\": \"Maintain equipment-tag, purchase-order, serial-number, and source-lot traceability.\"\n    },\n    {\n      \"parameter\": \"gen.source_lot\",\n      \"operator\": \"exists\",\n      \"value\": null,\n      \"unit\": null,\n      \"condition\": null,\n      \"quote\": \"Maintain equipment-tag, purchase-order, serial-number, and source-lot traceability.\"\n    }\n  ]\n}"}