{"content": "[\n  {\n    \"rule_id\": \"26 33 53 Part 1.4.1.A-R1\",\n    \"verdict\": \"NOT_ENOUGH_INFORMATION\",\n    \"page\": null,\n    \"quote\": \"\",\n    \"reason\": \"No mention of manufacturer experience years in package.\"\n  },\n  {\n    \"rule_id\": \"26 33 53 Part 1.4.1.A-R2\",\n    \"verdict\": \"NOT_ENOUGH_INFORMATION\",\n    \"page\": null,\n    \"quote\": \"\",\n    \"reason\": \"No reference installations listed in package.\"\n  },\n  {\n    \"rule_id\": \"26 33 53 Part 1.4.1.B-R1\",\n    \"verdict\": \"NOT_ENOUGH_INFORMATION\",\n    \"page\": null,\n    \"quote\": \"\",\n    \"reason\": \"No ISO 9001 certification mentioned in package.\"\n  },\n  {\n    \"rule_id\": \"26 33 53 Part 1.4.1.B-R2\",\n    \"verdict\": \"NOT_ENOUGH_INFORMATION\",\n    \"page\": null,\n    \"quote\": \"\",\n    \"reason\": \"No ISO 14001 certification mentioned in package.\"\n  },\n  {\n    \"rule_id\": \"26 33 53 Part 1.4.1.C-R1\",\n    \"verdict\": \"NOT_ENOUGH_INFORMATION\",\n    \"page\": null,\n    \"quote\": \"\",\n    \"reason\": \"No IEC 62040-3 certification mentioned in package.\"\n  },\n  {\n    \"rule_id\": \"26 33 53 Part 1.5.1.A-R1\",\n    \"verdict\": \"NOT_ENOUGH_INFORMATION\",\n    \"page\": null,\n    \"quote\": \"\",\n    \"reason\": \"No warranty duration mentioned in package.\"\n  },\n  {\n    \"rule_id\": \"26 33 53 Part 1.5.1.A-R2\",\n    \"verdict\": \"NOT_ENOUGH_INFORMATION\",\n    \"page\": null,\n    \"quote\": \"\",\n    \"reason\": \"No warranty component list mentioned in package.\"\n  },\n  {\n    \"rule_id\": \"26 33 53 Part 1.5.1.B-R1\",\n    \"verdict\": \"NOT_ENOUGH_INFORMATION\",\n    \"page\": null,\n    \"quote\": \"\",\n    \"reason\": \"No spare control boards mentioned in package.\"\n  },\n  {\n    \"rule_id\": \"26 33 53 Part 1.5.1.B-R2\",\n    \"verdict\": \"NOT_ENOUGH_INFORMATION\",\n    \"page\": null,\n    \"quote\": \"\",\n    \"reason\": \"No spare fan assembly mentioned in package.\"\n  },\n  {\n    \"rule_id\": \"26 33 53 Part 1.5.1.B-R3\",\n    \"verdict\": \"NOT_ENOUGH_INFORMATION\",\n    \"page\": null,\n    \"quote\": \"\",\n    \"reason\": \"No spare DC fuses mentioned in package.\"\n  },\n  {\n    \"rule_id\": \"26 33 53 Part 2.1.1.A-R1\",\n    \"verdict\": \"COMPLY\",\n    \"page\": 1,\n    \"quote\": \"VoltEdge Power Systems Submittal Package SUB-263353-02-R0\",\n    \"reason\": \"Package header shows manufacturer as VoltEdge Power Systems.\"\n  },\n  {\n    \"rule_id\": \"26 33 53 Part 2.1.2.A-R1\",\n    \"verdict\": \"NOT_ENOUGH_INFORMATION\",\n    \"page\": null,\n    \"quote\": \"\",\n    \"reason\": \"No redundancy configuration mentioned in package.\"\n  },\n  {\n    \"rule_id\": \"26 33 53 Part 2.1.2.A-R2\",\n    \"verdict\": \"NOT_ENOUGH_INFORMATION\",\n    \"page\": null,\n    \"quote\": \"\",\n    \"reason\": \"No mention of server halls or independent groups.\"\n  },\n  {\n    \"rule_id\": \"26 33 53 Part 2.2.1.A-R1\",\n    \"verdict\": \"NOT_ENOUGH_INFORMATION\",\n    \"page\": null,\n    \"quote\": \"\",\n    \"reason\": \"No output power rating mentioned in package.\"\n  },\n  {\n    \"rule_id\": \"26 33 53 Part 2.2.1.B-R1\",\n    \"verdict\": \"NOT_ENOUGH_INFORMATION\",\n    \"page\": null,\n    \"quote\": \"\",\n    \"reason\": \"No output power factor mentioned in package.\"\n  },\n  {\n    \"rule_id\": \"26 33 53 Part 2.2.1.C-R1\",\n    \"verdict\": \"NOT_ENOUGH_INFORMATION\",\n    \"page\": null,\n    \"quote\": \"\",\n    \"reason\": \"No topology mentioned in package.\"\n  },\n  {\n    \"rule_id\": \"26 33 53 Part 2.2.1.D-R1\",\n    \"verdict\": \"NOT_ENOUGH_INFORMATION\",\n    \"page\": null,\n    \"quote\": \"\",\n    \"reason\": \"No THDi mentioned in package.\"\n  },\n  {\n    \"rule_id\": \"26 33 53 Part 2.2.2.A-R1\",\n    \"verdict\": \"NOT_ENOUGH_INFORMATION\",\n    \"page\": null,\n    \"quote\": \"\",\n    \"reason\": \"No efficiency at 100% load mentioned in package.\"\n  },\n  {\n    \"rule_id\": \"26 33 53 Part 2.2.2.B-R1\",\n    \"verdict\": \"NOT_ENOUGH_INFORMATION\",\n    \"page\": null,\n    \"quote\": \"\",\n    \"reason\": \"No efficiency at 75% load mentioned in package.\"\n  },\n  {\n    \"rule_id\": \"26 33 53 Part 2.2.2.B-R2\",\n    \"verdict\": \"NOT_ENOUGH_INFORMATION\",\n    \"page\": null,\n    \"quote\": \"\",\n    \"reason\": \"No efficiency at 50% load mentioned in package.\"\n  },\n  {\n    \"rule_id\": \"26 33 53 Part 2.2.3.A-R1\",\n    \"verdict\": \"NOT_ENOUGH_INFORMATION\",\n    \"page\": null,\n    \"quote\": \"\",\n    \"reason\": \"No output voltage regulation mentioned in package.\"\n  },\n  {\n    \"rule_id\": \"26 33 53 Part 2.2.3.A-R2\",\n    \"verdict\": \"NOT_ENOUGH_INFORMATION\",\n    \"page\": null,\n    \"quote\": \"\",\n    \"reason\": \"No transient regulation mentioned in package.\"\n  },\n  {\n    \"rule_id\": \"26 33 53 Part 2.2.3.A-R3\",\n    \"verdict\": \"NOT_ENOUGH_INFORMATION\",\n    \"page\": null,\n    \"quote\": \"\",\n    \"reason\": \"No recovery time mentioned in package.\"\n  },\n  {\n    \"rule_id\": \"26 33 53 Part 2.2.4.A-R1\",\n    \"verdict\": \"NOT_ENOUGH_INFORMATION\",\n    \"page\": null,\n    \"quote\": \"\",\n    \"reason\": \"No frequency regulation mentioned in package.\"\n  },\n  {\n    \"rule_id\": \"26 33 53 Part 2.2.5.A-R1\",\n    \"verdict\": \"NOT_ENOUGH_INFORMATION\",\n    \"page\": null,\n    \"quote\": \"\",\n    \"reason\": \"No sustained overload mentioned in package.\"\n  }\n]"}